celeritas-0.9.0.data/purelib/celeritas/__init__.py
celeritas-0.9.0.data/purelib/celeritas/celeritas.py
celeritas-0.9.0.data/purelib/celeritas/dotnet.py
celeritas-0.9.0.data/purelib/celeritas/native/libCeleritas.Native.dylib
celeritas-0.9.0.dist-info/METADATA
celeritas-0.9.0.dist-info/WHEEL
celeritas-0.9.0.dist-info/top_level.txt
celeritas-0.9.0.dist-info/RECORD
