Metadata-Version: 2.4
Name: celeritas
Version: 0.9.0
Summary: High-Performance Music Engine - Python bindings for Celeritas
Home-page: https://github.com/sheinv78/Celeritas
Author: Vladimir V. Shein
Author-email: "Vladimir V. Shein" <sheinv78@gmail.com>
License: BSL-1.1
Project-URL: Homepage, https://github.com/sheinv78/Celeritas
Project-URL: Repository, https://github.com/sheinv78/Celeritas
Project-URL: Issues, https://github.com/sheinv78/Celeritas/issues
Keywords: music,audio,midi,music-theory,chord-analysis,simd
Classifier: Development Status :: 3 - Alpha
Classifier: Intended Audience :: Developers
Classifier: Topic :: Multimedia :: Sound/Audio
Classifier: Topic :: Software Development :: Libraries :: Python Modules
Classifier: License :: Other/Proprietary License
Classifier: Programming Language :: Python :: 3
Classifier: Programming Language :: Python :: 3.8
Classifier: Programming Language :: Python :: 3.9
Classifier: Programming Language :: Python :: 3.10
Classifier: Programming Language :: Python :: 3.11
Classifier: Programming Language :: Python :: 3.12
Requires-Python: >=3.8
Provides-Extra: dotnet
Requires-Dist: pythonnet>=3.0; extra == "dotnet"
Dynamic: author
Dynamic: home-page
Dynamic: requires-python
